django_find_similar/__init__.py
django_find_similar/admin.py
django_find_similar/apps.py
django_find_similar/forms.py
django_find_similar/package.py
django_find_similar/migrations/0001_initial.py
django_find_similar/migrations/__init__.py
django_find_similar/models/__init__.py
django_find_similar/models/adapter.py
django_find_similar/models/result.py
django_find_similar/models/text.py
django_find_similar/tests/__init__.py
django_find_similar/tests/test_adapter.py
django_find_similar/tests/test_forms.py
django_find_similar/tests/tests_models.py
django_find_similar-1.4.0.dist-info/LICENSE
django_find_similar-1.4.0.dist-info/METADATA
django_find_similar-1.4.0.dist-info/WHEEL
django_find_similar-1.4.0.dist-info/top_level.txt
django_find_similar-1.4.0.dist-info/RECORD
