Metadata-Version: 2.1
Name: django-find-similar
Version: 1.4.0
Summary: find-similar integration for django
Home-page: https://github.com/findsimilar/django-find-similar
Author: quillcraftsman
Author-email: quill@craftsman.lol
License: MIT
Project-URL: Documentation, https://dfs.craftsman.lol
Project-URL: Source, https://github.com/findsimilar/django-find-similar
Project-URL: Tracker, https://github.com/findsimilar/django-find-similar/issues
Project-URL: Release notes, https://github.com/findsimilar/django-find-similar/releases
Project-URL: Changelog, https://github.com/findsimilar/django-find-similar/releases
Project-URL: Download, https://pypi.org/project/django-find-similar/
Keywords: python,django,find-similar,integration
Classifier: Development Status :: 4 - Beta
Classifier: Intended Audience :: Developers
Classifier: License :: OSI Approved :: MIT License
Classifier: Programming Language :: Python :: 3
Classifier: Environment :: Web Environment
Classifier: Framework :: Django
Classifier: Operating System :: OS Independent
Classifier: Topic :: Utilities
Requires-Python: >=3
License-File: LICENSE
